{
	"name": "北师大版小学英语五年级单词",
	"children": [
		{
			"name": "北师大版小学英语五年级 上册",
			"children": [
				{
					"name": "a lot of"
				},
				{
					"name": "afraid"
				},
				{
					"name": "air"
				},
				{
					"name": "astronaut"
				},
				{
					"name": "become"
				},
				{
					"name": "dream"
				},
				{
					"name": "finally"
				},
				{
					"name": "friendly"
				},
				{
					"name": "had"
				},
				{
					"name": "last night"
				},
				{
					"name": "moon"
				},
				{
					"name": "planet"
				},
				{
					"name": "space"
				},
				{
					"name": "spaceship"
				},
				{
					"name": "star"
				},
				{
					"name": "then"
				},
				{
					"name": "was"
				},
				{
					"name": "were"
				},
				{
					"name": "yesterday"
				},
				{
					"name": "again"
				},
				{
					"name": "back"
				},
				{
					"name": "clean"
				},
				{
					"name": "cough"
				},
				{
					"name": "everywhere"
				},
				{
					"name": "give"
				},
				{
					"name": "make"
				},
				{
					"name": "next"
				},
				{
					"name": "pat"
				},
				{
					"name": "sick"
				},
				{
					"name": "slowly"
				},
				{
					"name": "visit"
				},
				{
					"name": "watch"
				},
				{
					"name": "because"
				},
				{
					"name": "competition"
				},
				{
					"name": "decide"
				},
				{
					"name": "eighth"
				},
				{
					"name": "excited"
				},
				{
					"name": "fast"
				},
				{
					"name": "fifth"
				},
				{
					"name": "first"
				},
				{
					"name": "fourth"
				},
				{
					"name": "happy"
				},
				{
					"name": "high"
				},
				{
					"name": "high jump"
				},
				{
					"name": "hundred"
				},
				{
					"name": "last"
				},
				{
					"name": "meter"
				},
				{
					"name": "ninth"
				},
				{
					"name": "prize"
				},
				{
					"name": "race"
				},
				{
					"name": "second"
				},
				{
					"name": "seventh"
				},
				{
					"name": "sixth"
				},
				{
					"name": "sport"
				},
				{
					"name": "sports day"
				},
				{
					"name": "tenth"
				},
				{
					"name": "third"
				},
				{
					"name": "thousand"
				},
				{
					"name": "win"
				},
				{
					"name": "April"
				},
				{
					"name": "August"
				},
				{
					"name": "autumn"
				},
				{
					"name": "birthday"
				},
				{
					"name": "calendar"
				},
				{
					"name": "check"
				},
				{
					"name": "date"
				},
				{
					"name": "December"
				},
				{
					"name": "February"
				},
				{
					"name": "forget"
				},
				{
					"name": "gift"
				},
				{
					"name": "invite"
				},
				{
					"name": "January"
				},
				{
					"name": "July"
				},
				{
					"name": "June"
				},
				{
					"name": "March"
				},
				{
					"name": "May"
				},
				{
					"name": "month"
				},
				{
					"name": "November"
				},
				{
					"name": "October"
				},
				{
					"name": "say"
				},
				{
					"name": "season"
				},
				{
					"name": "September"
				},
				{
					"name": "spring"
				},
				{
					"name": "summer"
				},
				{
					"name": "surprise"
				},
				{
					"name": "winter"
				},
				{
					"name": "year"
				},
				{
					"name": "center"
				},
				{
					"name": "centimeter"
				},
				{
					"name": "funny"
				},
				{
					"name": "heavy"
				},
				{
					"name": "height"
				},
				{
					"name": "kilogram"
				},
				{
					"name": "measure"
				},
				{
					"name": "one by one"
				},
				{
					"name": "or"
				},
				{
					"name": "scales"
				},
				{
					"name": "something"
				},
				{
					"name": "weigh"
				},
				{
					"name": "weight"
				},
				{
					"name": "why"
				},
				{
					"name": "wrong"
				},
				{
					"name": "many"
				},
				{
					"name": "photo"
				}
			]
		},
		{
			"name": "北师大版小学英语五年级 下册",
			"children": [
				{
					"name": "backpack"
				},
				{
					"name": "either"
				},
				{
					"name": "finally"
				},
				{
					"name": "find"
				},
				{
					"name": "Germany"
				},
				{
					"name": "get"
				},
				{
					"name": "give"
				},
				{
					"name": "go away"
				},
				{
					"name": "go home"
				},
				{
					"name": "hers"
				},
				{
					"name": "his"
				},
				{
					"name": "meet"
				},
				{
					"name": "mine"
				},
				{
					"name": "ours"
				},
				{
					"name": "quickly"
				},
				{
					"name": "suitcase"
				},
				{
					"name": "theirs"
				},
				{
					"name": "trip"
				},
				{
					"name": "yours"
				},
				{
					"name": "believe"
				},
				{
					"name": "concert"
				},
				{
					"name": "drum"
				},
				{
					"name": "flute"
				},
				{
					"name": "guitar"
				},
				{
					"name": "kid"
				},
				{
					"name": "music"
				},
				{
					"name": "piano"
				},
				{
					"name": "play the piano"
				},
				{
					"name": "program"
				},
				{
					"name": "really"
				},
				{
					"name": "start"
				},
				{
					"name": "tonight"
				},
				{
					"name": "violin"
				},
				{
					"name": "at last"
				},
				{
					"name": "at the same time"
				},
				{
					"name": "badminton"
				},
				{
					"name": "basketball"
				},
				{
					"name": "cheer for"
				},
				{
					"name": "corner kick"
				},
				{
					"name": "fall"
				},
				{
					"name": "field"
				},
				{
					"name": "goal"
				},
				{
					"name": "goalkeeper"
				},
				{
					"name": "row"
				},
				{
					"name": "score"
				},
				{
					"name": "sports star"
				},
				{
					"name": "table tennis"
				},
				{
					"name": "team"
				},
				{
					"name": "tennis"
				},
				{
					"name": "up and down"
				},
				{
					"name": "volleyball"
				},
				{
					"name": "boring"
				},
				{
					"name": "buy"
				},
				{
					"name": "colorful"
				},
				{
					"name": "dictionary"
				},
				{
					"name": "difficult"
				},
				{
					"name": "exciting"
				},
				{
					"name": "expensive"
				},
				{
					"name": "interesting"
				},
				{
					"name": "picture"
				},
				{
					"name": "story"
				},
				{
					"name": "a liter of milk"
				},
				{
					"name": "add"
				},
				{
					"name": "ask"
				},
				{
					"name": "bake"
				},
				{
					"name": "break"
				},
				{
					"name": "butter"
				},
				{
					"name": "change"
				},
				{
					"name": "cookbook"
				},
				{
					"name": "flour"
				},
				{
					"name": "guess"
				},
				{
					"name": "knife"
				},
				{
					"name": "mix"
				},
				{
					"name": "need"
				},
				{
					"name": "plate"
				},
				{
					"name": "pour"
				},
				{
					"name": "puzzled"
				},
				{
					"name": "recipe"
				},
				{
					"name": "salt"
				},
				{
					"name": "shout"
				},
				{
					"name": "step"
				},
				{
					"name": "sugar"
				},
				{
					"name": "tell"
				},
				{
					"name": "eat out"
				},
				{
					"name": "hate"
				},
				{
					"name": "try out"
				},
				{
					"name": "walk through"
				}
			]
		}
	]
}