{
	"name": "新版小学英语三年级单词",
	"classify": "小学英语",
	"children": [
		{
			"name": "新版小学英语三年级 上册",
			"children": [
				{
					"name": "bear"
				},
				{
					"name": "bird"
				},
				{
					"name": "cat"
				},
				{
					"name": "dog"
				},
				{
					"name": "duck"
				},
				{
					"name": "monkey"
				},
				{
					"name": "mouse"
				},
				{
					"name": "panda"
				},
				{
					"name": "pig"
				},
				{
					"name": "rabbit"
				},
				{
					"name": "bag"
				},
				{
					"name": "book"
				},
				{
					"name": "eraser"
				},
				{
					"name": "glue"
				},
				{
					"name": "pen"
				},
				{
					"name": "pencil"
				},
				{
					"name": "pencil box"
				},
				{
					"name": "ruler"
				},
				{
					"name": "scissors"
				},
				{
					"name": "sharpener"
				},
				{
					"name": "arm"
				},
				{
					"name": "ear"
				},
				{
					"name": "eye"
				},
				{
					"name": "face"
				},
				{
					"name": "foot"
				},
				{
					"name": "hand"
				},
				{
					"name": "head"
				},
				{
					"name": "knee"
				},
				{
					"name": "leg"
				},
				{
					"name": "mouth"
				},
				{
					"name": "neck"
				},
				{
					"name": "nose"
				},
				{
					"name": "ball"
				},
				{
					"name": "balloon"
				},
				{
					"name": "bike"
				},
				{
					"name": "boat"
				},
				{
					"name": "bus"
				},
				{
					"name": "car"
				},
				{
					"name": "doll"
				},
				{
					"name": "kite"
				},
				{
					"name": "plane"
				},
				{
					"name": "ship"
				},
				{
					"name": "taxi"
				},
				{
					"name": "train"
				},
				{
					"name": "black"
				},
				{
					"name": "blue"
				},
				{
					"name": "brown"
				},
				{
					"name": "green"
				},
				{
					"name": "grey"
				},
				{
					"name": "orange"
				},
				{
					"name": "pink"
				},
				{
					"name": "purple"
				},
				{
					"name": "red"
				},
				{
					"name": "white"
				},
				{
					"name": "yellow"
				},
				{
					"name": "apple"
				},
				{
					"name": "banana"
				},
				{
					"name": "cake"
				},
				{
					"name": "chicken"
				},
				{
					"name": "Coke"
				},
				{
					"name": "egg"
				},
				{
					"name": "hamburger"
				},
				{
					"name": "hot dog"
				},
				{
					"name": "juice"
				},
				{
					"name": "milk"
				},
				{
					"name": "noodles"
				},
				{
					"name": "orange"
				},
				{
					"name": "pear"
				},
				{
					"name": "rice"
				},
				{
					"name": "water"
				}
			]
		},
		{
			"name": "新版小学英语三年级 下册",
			"children": [
				{
					"name": "chair"
				},
				{
					"name": "Chinese book"
				},
				{
					"name": "classroom"
				},
				{
					"name": "crayon"
				},
				{
					"name": "desk"
				},
				{
					"name": "English book"
				},
				{
					"name": "marker"
				},
				{
					"name": "school"
				},
				{
					"name": "storybook"
				},
				{
					"name": "water bottle"
				},
				{
					"name": "eight"
				},
				{
					"name": "eleven"
				},
				{
					"name": "five"
				},
				{
					"name": "four"
				},
				{
					"name": "nine"
				},
				{
					"name": "one"
				},
				{
					"name": "seven"
				},
				{
					"name": "six"
				},
				{
					"name": "ten"
				},
				{
					"name": "three"
				},
				{
					"name": "twelve"
				},
				{
					"name": "two"
				},
				{
					"name": "aunt"
				},
				{
					"name": "brother"
				},
				{
					"name": "daughter"
				},
				{
					"name": "father"
				},
				{
					"name": "grandfather"
				},
				{
					"name": "grandmother"
				},
				{
					"name": "mother"
				},
				{
					"name": "sister"
				},
				{
					"name": "son"
				},
				{
					"name": "uncle"
				},
				{
					"name": "bread"
				},
				{
					"name": "candy"
				},
				{
					"name": "coffee"
				},
				{
					"name": "doughnut"
				},
				{
					"name": "fruit"
				},
				{
					"name": "grapes"
				},
				{
					"name": "honey"
				},
				{
					"name": "ice cream"
				},
				{
					"name": "jam"
				},
				{
					"name": "mango"
				},
				{
					"name": "elephant"
				},
				{
					"name": "kangaroo"
				},
				{
					"name": "lion"
				},
				{
					"name": "mosquito"
				},
				{
					"name": "nest"
				},
				{
					"name": "owl"
				},
				{
					"name": "parrot"
				},
				{
					"name": "quail"
				},
				{
					"name": "rooster"
				},
				{
					"name": "tiger"
				},
				{
					"name": "box"
				},
				{
					"name": "coat"
				},
				{
					"name": "skirt"
				},
				{
					"name": "sweater"
				},
				{
					"name": "T-shirt"
				},
				{
					"name": "uniform"
				},
				{
					"name": "vest"
				},
				{
					"name": "watch"
				},
				{
					"name": "yacht"
				},
				{
					"name": "zebra"
				},
				{
					"name": "zip"
				}
			]
		}
	]
}