{
	"name": "高中英语牛津版高三下学期",
	"classify": "高中英语",
	"children": [
		{
			"name": "A",
			"children": [
				"Alexander Graham Bell",
				"Austria",
				"abnormal",
				"accustomed",
				"acupuncture",
				"adapt",
				"adaptation",
				"adequate",
				"admire",
				"advisor",
				"amazement",
				"ambition",
				"amusement",
				"analyze",
				"anchovy",
				"appoint",
				"appointment",
				"arrival",
				"ashamed",
				"assistance",
				"associate",
				"assurance",
				"at random",
				"atlas",
				"atom",
				"attach",
				"attract",
				"awfully",
				"awkward"
			]
		},
		{
			"name": "B",
			"children": [
				"B.S.",
				"Bacchus",
				"baggage",
				"ball",
				"ballet",
				"bare",
				"barely",
				"bat",
				"beat",
				"beauty",
				"bind",
				"boom",
				"border",
				"bulb",
				"bury",
				"businessman",
				"by contrast"
			]
		},
		{
			"name": "C",
			"children": [
				"Canadian",
				"Cinderella",
				"calculate",
				"calmly",
				"campus",
				"capable",
				"career",
				"central",
				"central",
				"certainty",
				"chain",
				"char",
				"charcoal",
				"charge",
				"cheek",
				"choke",
				"cigar",
				"climate",
				"cloak",
				"comedy",
				"commercially",
				"compartment",
				"completely",
				"composer",
				"concern",
				"conduct",
				"conductor",
				"congress",
				"connection",
				"consequence",
				"considerable",
				"continental",
				"contrast",
				"cooking",
				"corridor",
				"couch",
				"creature",
				"curl",
				"cycle"
			]
		},
		{
			"name": "D",
			"children": [
				"Danish",
				"Danube",
				"Della",
				"Donald",
				"dangerously",
				"decision",
				"decoration",
				"degree",
				"delighted",
				"deposit",
				"desert",
				"design",
				"diet",
				"dine",
				"directly",
				"dirt",
				"disadvantage",
				"disconcert",
				"disobey",
				"distribute",
				"distrust",
				"document",
				"dominant",
				"donut",
				"dreadful",
				"drought",
				"drum",
				"duke",
				"duty"
			]
		},
		{
			"name": "F",
			"children": [
				"Florida",
				"Florida",
				"fabric",
				"faculty",
				"farmhouse",
				"fashionable",
				"favourable",
				"female",
				"fetch",
				"fish meal",
				"flash",
				"flat",
				"flee",
				"fluid",
				"foresee",
				"fortunately",
				"freely",
				"frighten",
				"function",
				"function"
			]
		},
		{
			"name": "G",
			"children": [
				"Glasgow",
				"generate",
				"generating station",
				"genius",
				"glittering",
				"gloomy",
				"glow",
				"grab",
				"gradually",
				"grandson",
				"grind",
				"groove",
				"grower",
				"guard",
				"gulf"
			]
		},
		{
			"name": "H",
			"children": [
				"Helen Keller",
				"halfway",
				"handicapped",
				"happening",
				"hopefully",
				"horror",
				"humiliating",
				"humour"
			]
		},
		{
			"name": "J",
			"children": [
				"Jim",
				"Jimmy",
				"jewel",
				"juicy"
			]
		},
		{
			"name": "K",
			"children": [
				"Kim",
				"keen",
				"kick",
				"king",
				"kiss",
				"knee"
			]
		},
		{
			"name": "M",
			"children": [
				"Mexican",
				"Mexico",
				"Midas",
				"madame",
				"mainly",
				"majority",
				"managing",
				"marigold",
				"meanwhile",
				"merger",
				"microscopic",
				"miraculous",
				"musician"
			]
		},
		{
			"name": "P",
			"children": [
				"Peru",
				"Peruvian",
				"Poland",
				"package",
				"package",
				"pale",
				"parallel",
				"participant",
				"particular",
				"patent",
				"pearl",
				"peculiar",
				"peeler",
				"peer",
				"peninsula",
				"permanently",
				"permission",
				"perspiration",
				"persuade",
				"phonograph",
				"physical",
				"pile",
				"pin",
				"plateau",
				"plentiful",
				"potato",
				"practiced",
				"predict",
				"press",
				"pride",
				"principal",
				"process",
				"producer",
				"productively",
				"profit",
				"programming",
				"proportion",
				"punch"
			]
		},
		{
			"name": "V",
			"children": [
				"Vienna",
				"vacuum",
				"vaguely",
				"vanish",
				"variety",
				"verb",
				"version",
				"viable",
				"vice versa",
				"vigour",
				"villager",
				"vine",
				"violin",
				"vote"
			]
		},
		{
			"name": "W",
			"children": [
				"Wells",
				"wage",
				"waltz",
				"warship",
				"washing-up",
				"waterfall",
				"wealth",
				"web",
				"weight",
				"well",
				"well-dressed",
				"wherever",
				"wine",
				"wire",
				"worthless",
				"wrench"
			]
		},
		{
			"name": "E",
			"children": [
				"eagerly",
				"eagerness",
				"eastward",
				"ecology",
				"economics",
				"economist",
				"edge",
				"educate",
				"empire",
				"enclose",
				"encourage",
				"encouragement",
				"endurance",
				"energy",
				"entirely",
				"equator",
				"error",
				"essential",
				"evidence",
				"exact",
				"examine",
				"excess fare",
				"experiment",
				"explanation",
				"expression",
				"extend"
			]
		},
		{
			"name": "I",
			"children": [
				"icy",
				"ignore",
				"imitate",
				"imperial",
				"implement",
				"importance",
				"impression",
				"impression",
				"imprint",
				"in particular",
				"inadequate",
				"incapable",
				"include",
				"income",
				"indirectly",
				"inland",
				"innocent",
				"inquiring",
				"insert",
				"inspiration",
				"interest",
				"interfere",
				"interviewer",
				"involve",
				"issue"
			]
		},
		{
			"name": "L",
			"children": [
				"lamb",
				"later on",
				"latitude",
				"lazy",
				"lean",
				"left-handed",
				"left-handedness",
				"left-hander",
				"light",
				"linen",
				"lip",
				"loan",
				"lump"
			]
		},
		{
			"name": "N",
			"children": [
				"napkin",
				"needle",
				"nevertheless",
				"newcomer",
				"novel",
				"numerous",
				"nursing",
				"nutrient"
			]
		},
		{
			"name": "O",
			"children": [
				"occupant",
				"officer",
				"one-sided",
				"opener",
				"operetta",
				"orchestra",
				"organ",
				"organism",
				"originally",
				"outer"
			]
		},
		{
			"name": "Q",
			"children": [
				"qualified"
			]
		},
		{
			"name": "R",
			"children": [
				"rabbit",
				"raiser",
				"random",
				"range",
				"range",
				"ray",
				"reduce",
				"refer",
				"reflection",
				"region",
				"regret",
				"reject",
				"relate",
				"remarkable",
				"reproduce",
				"resign",
				"rich",
				"right-handed",
				"right-hander",
				"robe",
				"root",
				"rot"
			]
		},
		{
			"name": "S",
			"children": [
				"saleable",
				"salt",
				"scarce",
				"scatter",
				"scenery",
				"scissors",
				"scratch",
				"seal",
				"secretly",
				"seed",
				"seemingly",
				"semitropical",
				"settle",
				"shade",
				"shadow",
				"shin",
				"shudder",
				"similar",
				"simplicity",
				"skip",
				"slowly",
				"smell",
				"soil",
				"someday",
				"somehow",
				"soup",
				"spill",
				"spirit",
				"spoonful",
				"spore",
				"spun",
				"square-jawed",
				"stable",
				"stammer",
				"stare",
				"starvation",
				"stem",
				"stock",
				"strap",
				"stutter",
				"stylus",
				"succeed",
				"successfully",
				"sunshine",
				"supervisor",
				"survive",
				"suspect",
				"symphony"
			]
		},
		{
			"name": "T",
			"children": [
				"take in",
				"talented",
				"tear",
				"telegrapher",
				"telegraphy",
				"temperate",
				"temporary",
				"tendency",
				"terror",
				"test",
				"the Antarctic Ocean",
				"the Crimean War",
				"the Rocky Mountains",
				"theory",
				"thread",
				"thread",
				"tightly",
				"tin",
				"tinfoil",
				"tiny",
				"toe",
				"total",
				"totally",
				"touch",
				"tour",
				"transmit",
				"transplant",
				"treasury",
				"trial",
				"trial and error",
				"tropics",
				"tune",
				"typewrite"
			]
		},
		{
			"name": "U",
			"children": [
				"unfair",
				"unfamiliar",
				"unfavourable",
				"uninhabitable",
				"unite",
				"unless",
				"unlighted",
				"unpleasant",
				"unrelated"
			]
		},
		{
			"name": "Z",
			"children": [
				"zone"
			]
		}
	]
}